numpy_flow/__init__.py
numpy_flow-0.0.1.dist-info/LICENSE
numpy_flow-0.0.1.dist-info/METADATA
numpy_flow-0.0.1.dist-info/WHEEL
numpy_flow-0.0.1.dist-info/top_level.txt
numpy_flow-0.0.1.dist-info/RECORD
