Metadata-Version: 2.1
Name: numpy-flow
Version: 0.0.1
Summary: Nothing at all.
Home-page: https://github.com/zhangdongkun98/numpy-flow
Author: Zhang Dongkun
Author-email: zhangdongkun98@gmail.com
License: UNKNOWN
Platform: UNKNOWN
